AUTHORS
LICENSE
MANIFEST.in
README.rst
setup.py
src/restible_appengine/__init__.py
src/restible_appengine/resource.py
src/restible_appengine/util.py
src/restible_appengine.egg-info/PKG-INFO
src/restible_appengine.egg-info/SOURCES.txt
src/restible_appengine.egg-info/dependency_links.txt
src/restible_appengine.egg-info/requires.txt
src/restible_appengine.egg-info/top_level.txt
src/restible_appengine/secure/__init__.py
src/restible_appengine/secure/decorators.py
src/restible_appengine/secure/endpoint.py
src/restible_appengine/secure/util.py