Metadata-Version: 1.1
Name: restible-appengine
Version: 0.3.5
Summary: AppEngine integration for restible library
Home-page: https://github.com/novopl/restible-appengine
Author: Mateusz 'novo' Klos
Author-email: novopl@gmail.com
License: MIT
Keywords: restible REST restapi rest server appengine
Platform: UNKNOWN
Classifier: Development Status :: 4 - Beta
Classifier: Topic :: Utilities
Classifier: Intended Audience :: Developers
Classifier: Programming Language :: Python
Classifier: License :: OSI Approved :: MIT License
